CHANGELOG.md
weasel.py
weasel_cli-1.0.4.dist-info/entry_points.txt
weasel_cli-1.0.4.dist-info/LICENSE
weasel_cli-1.0.4.dist-info/WHEEL
weasel_cli-1.0.4.dist-info/METADATA
weasel_cli-1.0.4.dist-info/RECORD
