Metadata-Version: 2.1
Name: weasel-cli
Version: 1.0.4
Summary: Simulate Dawkins' weasel experiment
Home-page: https://github.com/wdsrocha/weasel-cli
License: MIT
Author: Wesley Rocha
Author-email: wesleysr1997@gmail.com
Requires-Python: >=3.6,<4.0
Classifier: License :: OSI Approved :: MIT License
Classifier: Programming Language :: Python :: 3
Classifier: Programming Language :: Python :: 3.6
Classifier: Programming Language :: Python :: 3.7
Classifier: Programming Language :: Python :: 3.8
Requires-Dist: click (>=7.1.2,<8.0.0)
Project-URL: Repository, https://github.com/wdsrocha/weasel-cli
